setup.py
RASD_TOOLBOX/RASD.py
RASD_TOOLBOX/__init__.py
RASD_TOOLBOX.egg-info/PKG-INFO
RASD_TOOLBOX.egg-info/SOURCES.txt
RASD_TOOLBOX.egg-info/dependency_links.txt
RASD_TOOLBOX.egg-info/requires.txt
RASD_TOOLBOX.egg-info/top_level.txt